zenmoney/__init__.py
zenmoney/account.py
zenmoney/budget.py
zenmoney/company.py
zenmoney/deletion.py
zenmoney/diff.py
zenmoney/exception.py
zenmoney/instrument.py
zenmoney/merchant.py
zenmoney/oauth2.py
zenmoney/reminder.py
zenmoney/reminder_marker.py
zenmoney/request.py
zenmoney/tag.py
zenmoney/transaction.py
zenmoney/user.py
zenmoney/zenobject.py
zenmoney-0.9.dist-info/LICENSE
zenmoney-0.9.dist-info/METADATA
zenmoney-0.9.dist-info/WHEEL
zenmoney-0.9.dist-info/top_level.txt
zenmoney-0.9.dist-info/RECORD
