Metadata-Version: 2.1
Name: zenmoney
Version: 0.9
Summary: Library for zenmoney.ru API
Home-page: https://github.com/Felixoid/python-zenmoney
Author: Mikhail f. Shiryaev
Author-email: mr.felixoid@gmail.com
License: MIT
Platform: UNKNOWN
Classifier: Development Status :: 4 - Beta
Classifier: License :: OSI Approved :: MIT License
Classifier: Environment :: Console
Classifier: Programming Language :: Python :: 3
Classifier: Operating System :: OS Independent
Requires-Python: >=3
Requires-Dist: requests
